rss/template/people.rss.see
rss/template/xinhua.rss.see
seesea-static/html/assets/index-BmKde2Y3.js
seesea-static/html/assets/index-DbwnZPkQ.js
seesea-static/html/assets/index-vcA4qu3D.js
seesea-static/html/assets/index-xVI9yBTE.js
seesea-static/html/favicon.ico
seesea-static/html/index.html
seesea_core/__init__.py
seesea_core/seesea_core.abi3.so
seesea_core-2.1.1.dist-info/METADATA
seesea_core-2.1.1.dist-info/WHEEL
seesea_core.libs/libcrypto-3d51e64a.so.3
seesea_core.libs/libssl-f23c6de6.so.3
seesea_core-2.1.1.dist-info/RECORD
