Metadata-Version: 2.4
Name: seesea-core
Version: 2.1.1
Classifier: Development Status :: 4 - Beta
Classifier: Intended Audience :: Developers
Classifier: License :: OSI Approved :: GNU Affero General Public License v3 or later (AGPLv3+)
Classifier: Programming Language :: Python :: 3
Classifier: Programming Language :: Python :: 3.10
Classifier: Programming Language :: Python :: 3.11
Classifier: Programming Language :: Python :: 3.12
Classifier: Programming Language :: Python :: 3.13
Classifier: Programming Language :: Python :: 3.14
Classifier: Programming Language :: Rust
Classifier: Topic :: Internet :: WWW/HTTP :: Indexing/Search
Classifier: Topic :: Internet :: WWW/HTTP :: Dynamic Content :: News/Diary
Classifier: Topic :: Software Development :: Libraries :: Python Modules
Summary: SeeSea Rust core module - High-performance privacy-focused data aggregation platform
Keywords: search,metasearch,privacy,rust,rss,hot-trends,ai,vector-database
Author-email: nostalgiatan <heavenly@nostalgiatan.top>
License: AGPL-3.0-or-later
Requires-Python: >=3.10
